simple_safe/__init__.py
simple_safe/abi.py
simple_safe/auth.py
simple_safe/chaindata.py
simple_safe/click.py
simple_safe/console.py
simple_safe/constants.py
simple_safe/params.py
simple_safe/py.typed
simple_safe/safe.py
simple_safe/types.py
simple_safe/util.py
simple_safe/validation.py
simple_safe/workflows.py
simple_safe/abis/CreateCall.abi
simple_safe/docs/README.md
simple_safe-0.3.0.dist-info/METADATA
simple_safe-0.3.0.dist-info/WHEEL
simple_safe-0.3.0.dist-info/entry_points.txt
simple_safe-0.3.0.dist-info/licenses/LICENSE
simple_safe-0.3.0.dist-info/RECORD
