Metadata-Version: 2.4
Name: simple-safe
Version: 0.3.0
Summary: A simple Web3-native CLI for Safe multisig wallets
Project-URL: Homepage, https://github.com/clearmatics/simple-safe
Project-URL: Source, https://github.com/clearmatics/simple-safe
Project-URL: Issues, https://github.com/clearmatics/simple-safe/issues
Project-URL: Changes, https://github.com/clearmatics/simple-safe/blob/master/CHANGELOG.md
License-Expression: MIT
License-File: LICENSE
Keywords: ethereum,safe,web3
Classifier: Development Status :: 4 - Beta
Classifier: Intended Audience :: End Users/Desktop
Classifier: License :: OSI Approved :: MIT License
Classifier: Programming Language :: Python
Classifier: Programming Language :: Python :: 3.11
Classifier: Programming Language :: Python :: 3.12
Classifier: Programming Language :: Python :: 3.13
Classifier: Topic :: Office/Business :: Financial
Classifier: Topic :: Utilities
Requires-Python: >=3.11
Requires-Dist: click-option-group>=0.5.7
Requires-Dist: click>=8.1.8
Requires-Dist: platformdirs>=4.3.8
Requires-Dist: requests>=2.32.4
Requires-Dist: rich>=14.0.0
Requires-Dist: safe-eth-py>=7.3.0
Requires-Dist: tomli-w>=1.2.0
Requires-Dist: trezor[ethereum]>=0.13.10
